sidetrek/README.md
sidetrek/__init__.py
sidetrek/ipython/magics.py
sidetrek/nbdev/directives.py
sidetrek/nbdev/export.py
sidetrek/trino.py
sidetrek-0.1.4.dist-info/LICENSE
sidetrek-0.1.4.dist-info/METADATA
sidetrek-0.1.4.dist-info/WHEEL
sidetrek-0.1.4.dist-info/RECORD
