Metadata-Version: 2.1
Name: sidetrek
Version: 0.1.4
Summary: 
Author: Seungchan Lee
Author-email: seunggs@gmail.com
Requires-Python: >=3.10,<3.13
Classifier: Programming Language :: Python :: 3
Classifier: Programming Language :: Python :: 3.10
Classifier: Programming Language :: Python :: 3.11
Classifier: Programming Language :: Python :: 3.12
Requires-Dist: nbdev (>=2.3.25,<3.0.0)
Requires-Dist: setuptools (>=71.1.0,<72.0.0)
Requires-Dist: trino (>=0.329.0,<0.330.0)
